LICENSE
MANIFEST.in
README.md
setup.cfg
setup.py
docs/usages.txt
src/py3toolbox/__init__.py
src/py3toolbox/constants.py
src/py3toolbox/daemon_tools.py
src/py3toolbox/dict_tools.py
src/py3toolbox/fs_tools.py
src/py3toolbox/gdrive_tools.py
src/py3toolbox/helper.py
src/py3toolbox/html_tools.py
src/py3toolbox/img_tools.py
src/py3toolbox/json_tools.py
src/py3toolbox/mail_tools.py
src/py3toolbox/media_tools.py
src/py3toolbox/mouse_tools.py
src/py3toolbox/net_tools.py
src/py3toolbox/os_tools.py
src/py3toolbox/print_tools.py
src/py3toolbox/security_tools.py
src/py3toolbox/text_tools.py
src/py3toolbox/time_tools.py
src/py3toolbox/web_tools.py
src/py3toolbox/xml_tools.py
src/py3toolbox.egg-info/PKG-INFO
src/py3toolbox.egg-info/SOURCES.txt
src/py3toolbox.egg-info/dependency_links.txt
src/py3toolbox.egg-info/requires.txt
src/py3toolbox.egg-info/top_level.txt