Metadata-Version: 2.1
Name: py3toolbox
Version: 0.1.69
Summary: A Python3 tools and utilities collection
Home-page: https://github.com/gr82morozr/py3toolbox.git
Author: Great Tomorrow
Author-email: gr82morozr@gmail.com
License: MIT
Keywords: toolbox
Platform: UNKNOWN
Classifier: Programming Language :: Python :: 3
Classifier: License :: OSI Approved :: MIT License
Classifier: Operating System :: OS Independent
Requires-Python: >=3.6
License-File: LICENSE
